qiskit_trebugger/__init__.py
qiskit_trebugger/debugger.py
qiskit_trebugger/debugger_error.py
qiskit_trebugger/model/__init__.py
qiskit_trebugger/model/circuit_comparator.py
qiskit_trebugger/model/circuit_stats.py
qiskit_trebugger/model/data_collector.py
qiskit_trebugger/model/log_entry.py
qiskit_trebugger/model/logging_handler.py
qiskit_trebugger/model/pass_type.py
qiskit_trebugger/model/property.py
qiskit_trebugger/model/transpilation_sequence.py
qiskit_trebugger/model/transpilation_step.py
qiskit_trebugger/views/__init__.py
qiskit_trebugger/views/cli/__init__.py
qiskit_trebugger/views/cli/cli_pass_pad.py
qiskit_trebugger/views/cli/cli_view.py
qiskit_trebugger/views/cli/config.py
qiskit_trebugger/views/widget/__init__.py
qiskit_trebugger/views/widget/button_with_value.py
qiskit_trebugger/views/widget/timeline_utils.py
qiskit_trebugger/views/widget/timeline_view.py
qiskit_trebugger-1.1.2.dist-info/LICENSE
qiskit_trebugger-1.1.2.dist-info/METADATA
qiskit_trebugger-1.1.2.dist-info/WHEEL
qiskit_trebugger-1.1.2.dist-info/top_level.txt
qiskit_trebugger-1.1.2.dist-info/RECORD
