Metadata-Version: 2.1
Name: qiskit-trebugger
Version: 1.1.2
Summary: A timeline debugger for the qiskit transpiler
Home-page: https://github.com/TheGupta2012/qiskit-timeline-debugger
Author: Egretta Thula, Harshit Gupta
Author-email: harshit.11235@gmail.com
Classifier: Programming Language :: Python :: 3
Classifier: License :: OSI Approved :: Apache Software License
Classifier: Operating System :: OS Independent
Requires-Python: >=3.8
License-File: LICENSE
Requires-Dist: ipython >=8.12.0
Requires-Dist: ipywidgets ==7.6.5
Requires-Dist: numpy ==1.22.2
Requires-Dist: qiskit ==0.43.0
Requires-Dist: qiskit-ignis ==0.7.0
Requires-Dist: tabulate ==0.9.0
Requires-Dist: matplotlib >=3.3
Requires-Dist: pylatexenc >=1.4
